<?xml version = '1.0' encoding = 'UTF-8'?>
<TableProxyOraclev11g class="oracle.dbtools.crest.model.design.storage.oracle.v11g.TableProxyOraclev11g" name="consultant" directorySegmentName="seg_0" id="D70FDA37-5156-3BD8-D217-3221B17B48F4">
<createdBy>eisti</createdBy>
<createdTime>2016-11-02 09:08:37 UTC</createdTime>
<ownerDesignName>oify_mcd_v2</ownerDesignName>
<partitionedRowMovement>DISABLE</partitionedRowMovement>
<temporaryChanged>false</temporaryChanged>
<accessDriverType>oracle_loader</accessDriverType>
<rejectLimit></rejectLimit>
<columnProxies itemClass="oracle.dbtools.crest.model.design.storage.oracle.v12c.ColumnProxyOraclev12c">
<ColumnProxy name="prenom" id="01DB6916-4B6C-5223-64DC-6AB8D4097A1D">
<createdBy>eisti</createdBy>
<createdTime>2016-11-02 09:08:37 UTC</createdTime>
<ownerDesignName>oify_mcd_v2</ownerDesignName>
</ColumnProxy>
<ColumnProxy name="role_id" id="05F17910-0F84-521E-5002-B79BE89E7786">
<createdBy>eisti</createdBy>
<createdTime>2016-11-02 09:08:37 UTC</createdTime>
<ownerDesignName>oify_mcd_v2</ownerDesignName>
</ColumnProxy>
<ColumnProxy name="id_consultant" id="396A04FB-D5EF-DA74-F0BE-AD7A22A5D53B">
<createdBy>eisti</createdBy>
<createdTime>2016-11-02 09:08:37 UTC</createdTime>
<ownerDesignName>oify_mcd_v2</ownerDesignName>
</ColumnProxy>
<ColumnProxy name="username" id="A598A4D7-3F34-CE74-9FE3-6CF0BBE406F3">
<createdBy>eisti</createdBy>
<createdTime>2016-11-02 09:08:37 UTC</createdTime>
<ownerDesignName>oify_mcd_v2</ownerDesignName>
</ColumnProxy>
<ColumnProxy name="password" id="AED0005D-E0D9-D157-7D2E-4DA5FAA16A71">
<createdBy>eisti</createdBy>
<createdTime>2016-11-02 09:08:37 UTC</createdTime>
<ownerDesignName>oify_mcd_v2</ownerDesignName>
</ColumnProxy>
<ColumnProxy name="nom" id="BE1A3FC3-7C56-0B3F-442A-FE1A8DDA8B82">
<createdBy>eisti</createdBy>
<createdTime>2016-11-02 09:08:37 UTC</createdTime>
<ownerDesignName>oify_mcd_v2</ownerDesignName>
</ColumnProxy>
</columnProxies>
<foreignKeys>
<ForeignKey class="oracle.dbtools.crest.model.design.storage.oracle.v10g.FKProxyOraclev10g" name="consultant_role_FK" id="860BE3D2-12B3-BF95-FCDC-3BD0DDA13D13">
<createdBy>eisti</createdBy>
<createdTime>2016-11-02 09:08:37 UTC</createdTime>
<ownerDesignName>oify_mcd_v2</ownerDesignName>
</ForeignKey>
</foreignKeys>
<primaryKeys>
<PrimaryKey class="oracle.dbtools.crest.model.design.storage.oracle.v10g.PKProxyOraclev10g" name="consultant_PK" id="C4086BE8-F370-1EBD-F490-34370DEAF1B0">
<createdBy>eisti</createdBy>
<createdTime>2016-11-02 09:08:37 UTC</createdTime>
<ownerDesignName>oify_mcd_v2</ownerDesignName>
<indexSort>SORTED</indexSort>
</PrimaryKey>
</primaryKeys>
</TableProxyOraclev11g>